pyisic/__init__.py
pyisic/types.py
pyisic/_standards/__init__.py
pyisic/_standards/ateco/__init__.py
pyisic/_standards/ateco/ateco.py
pyisic/_standards/ateco/ateco_to_nace2.py
pyisic/_standards/caem2005/__init__.py
pyisic/_standards/caem2005/caem2005.py
pyisic/_standards/caem2005/caem2005_to_caem2009.py
pyisic/_standards/caem2005/caem2005_to_isic3.py
pyisic/_standards/caem2009/__init__.py
pyisic/_standards/caem2009/caem2009.py
pyisic/_standards/caem2009/caem2009_to_isic4.py
pyisic/_standards/ccnae2021/__init__.py
pyisic/_standards/ccnae2021/ccnae2021.py
pyisic/_standards/ccnae2021/ccnae2021_to_isic4.py
pyisic/_standards/cnae2/__init__.py
pyisic/_standards/cnae2/cnae2.py
pyisic/_standards/cnae2/cnae2_to_isic4.py
pyisic/_standards/gced2011/__init__.py
pyisic/_standards/gced2011/gced2011.py
pyisic/_standards/gced2011/gced2011_to_nace2.py
pyisic/_standards/isic3/__init__.py
pyisic/_standards/isic3/isic3.py
pyisic/_standards/isic3/isic3_to_isic31.py
pyisic/_standards/isic31/__init__.py
pyisic/_standards/isic31/isic31.py
pyisic/_standards/isic31/isic31_to_isic4.py
pyisic/_standards/isic4/__init__.py
pyisic/_standards/isic4/isic4.py
pyisic/_standards/jsic13/__init__.py
pyisic/_standards/jsic13/jsic13.py
pyisic/_standards/jsic13/jsic13_to_isic4.py
pyisic/_standards/ksic10/__init__.py
pyisic/_standards/ksic10/ksic10.py
pyisic/_standards/ksic10/ksic10_to_isic4.py
pyisic/_standards/nace1/__init__.py
pyisic/_standards/nace1/nace1.py
pyisic/_standards/nace1/nace1_to_nace2.py
pyisic/_standards/nace2/__init__.py
pyisic/_standards/nace2/nace2.py
pyisic/_standards/nace2/nace2_to_isic4.py
pyisic/_standards/nacebel2003/__init__.py
pyisic/_standards/nacebel2003/nacebel2003.py
pyisic/_standards/nacebel2003/nacebel2003_to_nacebel2008.py
pyisic/_standards/nacebel2008/__init__.py
pyisic/_standards/nacebel2008/nacebel2008.py
pyisic/_standards/nacebel2008/nacebel2008_to_nace2.py
pyisic/_standards/naf1/__init__.py
pyisic/_standards/naf1/naf1.py
pyisic/_standards/naf1/naf1_to_naf2.py
pyisic-0.1.24.dist-info/licenses/LICENSE
pyisic-0.1.24.dist-info/METADATA
pyisic-0.1.24.dist-info/WHEEL
pyisic-0.1.24.dist-info/top_level.txt
pyisic-0.1.24.dist-info/RECORD
